dash_vizzu/DashVizzu.py
dash_vizzu/__init__.py
dash_vizzu/_imports_.py
dash_vizzu/async-DashVizzu.js
dash_vizzu/async-DashVizzu.js.map
dash_vizzu/dash_vizzu.min.js
dash_vizzu/dash_vizzu.min.js.map
dash_vizzu/metadata.json
dash_vizzu/package-info.json
dash_vizzu-0.0.1.dist-info/LICENSE
dash_vizzu-0.0.1.dist-info/METADATA
dash_vizzu-0.0.1.dist-info/WHEEL
dash_vizzu-0.0.1.dist-info/top_level.txt
dash_vizzu-0.0.1.dist-info/RECORD
