Metadata-Version: 2.1
Name: dash-vizzu
Version: 0.0.1
Summary: Wrapper for Vizzu in Dash
Author: José Luiz Ferreira <jlfsjunior@gmail.com>
License: MIT
Platform: UNKNOWN
Classifier: Framework :: Dash
License-File: LICENSE
